pixhawkcontroller/__init__.py
pixhawkcontroller/__version__.py
pixhawkcontroller/main.py
pixhawkcontroller-0.0.2.dist-info/licenses/LICENSE
pixhawkcontroller-0.0.2.dist-info/METADATA
pixhawkcontroller-0.0.2.dist-info/WHEEL
pixhawkcontroller-0.0.2.dist-info/top_level.txt
pixhawkcontroller-0.0.2.dist-info/RECORD
