Metadata-Version: 2.4
Name: pixhawkcontroller
Version: 0.0.2
Summary: Lightweight Pixhawk/ArduPilot controller utilities using pymavlink
Home-page: https://github.com/Shahriar88/pixhawkcontroller
Author: Md Shahriar Forhad
Author-email: shahriar.forhad.eee@gmail.com
License: MIT
Project-URL: Source, https://github.com/Shahriar88/pixhawkcontroller
Project-URL: Issues, https://github.com/Shahriar88/pixhawkcontroller/issues
Keywords: pixhawk,ardupilot,mavlink,pymavlink,drone,uav
Classifier: Development Status :: 3 - Alpha
Classifier: License :: OSI Approved :: MIT License
Classifier: Programming Language :: Python :: 3 :: Only
Classifier: Programming Language :: Python :: 3.9
Classifier: Programming Language :: Python :: 3.10
Classifier: Programming Language :: Python :: 3.11
Classifier: Programming Language :: Python :: 3.12
Classifier: Operating System :: OS Independent
Classifier: Topic :: Scientific/Engineering
Classifier: Topic :: System :: Hardware
Classifier: Topic :: Software Development :: Libraries
Requires-Python: >=3.9
License-File: LICENSE
Requires-Dist: pymavlink>=2.4.41
Requires-Dist: pyserial>=3.5
Provides-Extra: dev
Requires-Dist: build==1.3.0; extra == "dev"
Requires-Dist: setuptools==80.9.0; extra == "dev"
Requires-Dist: wheel==0.45.1; extra == "dev"
Requires-Dist: twine==6.2.0; extra == "dev"
Requires-Dist: packaging==25.0; extra == "dev"
Dynamic: author
Dynamic: author-email
Dynamic: classifier
Dynamic: description
Dynamic: description-content-type
Dynamic: home-page
Dynamic: keywords
Dynamic: license
Dynamic: license-file
Dynamic: project-url
Dynamic: provides-extra
Dynamic: requires-dist
Dynamic: requires-python
Dynamic: summary
